CONTRIBUTORS.md
LICENSE
MANIFEST.in
README.rst
setup.py
ytrans/__init__.py
ytrans/exceptions.py
ytrans/settings.py
ytrans/utils.py
ytrans.egg-info/PKG-INFO
ytrans.egg-info/SOURCES.txt
ytrans.egg-info/dependency_links.txt
ytrans.egg-info/not-zip-safe
ytrans.egg-info/top_level.txt
ytrans/bin/ytrans-interactive.py
ytrans/bin/ytranslate.py