Metadata-Version: 1.1
Name: ytrans
Version: 0.1.1
Summary: Unoficial client for yandex translator
Home-page: https://github.com/rkashapov/yandex-translator
Author: Emmanuel Odeke, Rustam Kashapov
Author-email: hardtechnik91@gmail.com
License: MIT License
Platform: UNKNOWN
Classifier: Development Status :: 3 - Alpha
Classifier: Operating System :: OS Independent
Classifier: Programming Language :: Python
Classifier: Programming Language :: Python :: 2
Classifier: Programming Language :: Python :: 2.7
Classifier: Programming Language :: Python :: 3
Classifier: Programming Language :: Python :: 3.3
Classifier: Programming Language :: Python :: 3.4
Classifier: Topic :: Internet :: WWW/HTTP
Classifier: Topic :: Software Development :: Libraries :: Python Modules
